exencolorlogs/__init__.py
exencolorlogs/colorlog.py
exencolorlogs-1.0.2.dist-info/LICENSE
exencolorlogs-1.0.2.dist-info/WHEEL
exencolorlogs-1.0.2.dist-info/METADATA
exencolorlogs-1.0.2.dist-info/RECORD
